examples/__init__.py
examples/simple_requests.py
leanplum/__init__.py
leanplum/client.py
leanplum/errors.py
leanplum/http_client.py
leanplum/logger.py
leanplum/requestor.py
leanplum/response.py
leanplum/actions/__init__.py
leanplum/actions/abstract.py
leanplum/actions/admin.py
leanplum/actions/disposition.py
leanplum/actions/users.py
python_leanplum-0.6.0.dist-info/LICENSE
python_leanplum-0.6.0.dist-info/METADATA
python_leanplum-0.6.0.dist-info/WHEEL
python_leanplum-0.6.0.dist-info/top_level.txt
python_leanplum-0.6.0.dist-info/RECORD
