Metadata-Version: 2.1
Name: python-leanplum
Version: 0.6.0
Summary: Python 3 API wrapper for LeanPlum
Home-page: https://github.com/sandboxxapp/python-leanplum
Author: Tim Chen / Eric Pluntze / Sam Clements / Jesse Li
Author-email: tim@sandboxx.us
License: UNKNOWN
Project-URL: Bug Tracker, https://github.com/pypa/sampleproject/issues
Platform: UNKNOWN
Classifier: Programming Language :: Python :: 3
Classifier: License :: OSI Approved :: MIT License
Classifier: Operating System :: OS Independent
Requires-Python: >=3.6
License-File: LICENSE
